pybinpack/__init__.py
pybinpack/__main__.py
pybinpack/_util.py
pybinpack/_version.py
pybinpack/cargo.py
pybinpack/py.typed
pybinpack-0.1.0.dist-info/METADATA
pybinpack-0.1.0.dist-info/WHEEL
pybinpack-0.1.0.dist-info/entry_points.txt
pybinpack-0.1.0.dist-info/licenses/LICENSE.txt
pybinpack-0.1.0.dist-info/RECORD
